setup.cfg
setup.py
pywin_env_shift/__init___.py
pywin_env_shift/main.py
pywin_env_shift.egg-info/PKG-INFO
pywin_env_shift.egg-info/SOURCES.txt
pywin_env_shift.egg-info/dependency_links.txt
pywin_env_shift.egg-info/top_level.txt