Metadata-Version: 1.0
Name: pywin-env-shift
Version: 0.1.1
Summary: A package to help deploy your venv
Home-page: https://github.com/psneo/pywin_env_shift
Author: psneo
Author-email: UNKNOWN
License: LICENSE.txt
Platform: UNKNOWN
